raiden_libs/__init__.py
raiden_libs/blockchain.py
raiden_libs/contract.py
raiden_libs/exceptions.py
raiden_libs/gevent_error_handler.py
raiden_libs/no_ssl_patch.py
raiden_libs/private_contract.py
raiden_libs/types.py
raiden_libs/messages/__init__.py
raiden_libs/messages/balance_proof.py
raiden_libs/messages/deserializer.py
raiden_libs/messages/fee_info.py
raiden_libs/messages/json_schema.py
raiden_libs/messages/message.py
raiden_libs/messages/monitor_request.py
raiden_libs/messages/paths_reply.py
raiden_libs/messages/paths_request.py
raiden_libs/network/__init__.py
raiden_libs/network/matrix/__init__.py
raiden_libs/network/matrix/client.py
raiden_libs/network/matrix/room.py
raiden_libs/properties/__init__.py
raiden_libs/properties/address.py
raiden_libs/test/__init__.py
raiden_libs/test/fixtures/__init__.py
raiden_libs/test/fixtures/address.py
raiden_libs/test/fixtures/client.py
raiden_libs/test/fixtures/web3.py
raiden_libs/test/mocks/__init__.py
raiden_libs/test/mocks/blockchain.py
raiden_libs/test/mocks/client.py
raiden_libs/test/mocks/dummy_transport.py
raiden_libs/transport/__init__.py
raiden_libs/transport/matrix.py
raiden_libs/transport/transport.py
raiden_libs/utils/__init__.py
raiden_libs/utils/contracts.py
raiden_libs/utils/merkle.py
raiden_libs/utils/private_key.py
raiden_libs/utils/signing.py
raiden_libs-0.1.16.dist-info/METADATA
raiden_libs-0.1.16.dist-info/WHEEL
raiden_libs-0.1.16.dist-info/top_level.txt
raiden_libs-0.1.16.dist-info/RECORD
