Metadata-Version: 1.1
Name: raiden_libs
Version: 0.1.16
Summary: Useful tools for Raiden and services.
Home-page: https://github.com/raiden-network/raiden_libs
Author: Brainbot Labs Est.
Author-email: contact@brainbot.li
License: UNKNOWN
Keywords: raiden_libs
Platform: UNKNOWN
Classifier: Development Status :: 2 - Pre-Alpha
Classifier: Intended Audience :: Developers
Classifier: Natural Language :: English
Classifier: Programming Language :: Python :: 3
Classifier: Programming Language :: Python :: 3.6
